MANIFEST.in
README.md
requirements.txt
setup.cfg
setup.py
pim/__init__.py
pim/cli.py
pim/utils.py
pim.egg-info/PKG-INFO
pim.egg-info/SOURCES.txt
pim.egg-info/dependency_links.txt
pim.egg-info/entry_points.txt
pim.egg-info/requires.txt
pim.egg-info/top_level.txt
pim/commands/__init__.py
pim/commands/init.py
pim/commands/install.py
pim/commands/ls.py
pim/commands/uninstall.py
pim/templates/MANIFEST.in.txt
pim/templates/__init__.py.txt
pim/templates/setup.cfg.txt
pim/templates/setup.py.txt