Metadata-Version: 1.0
Name: pim
Version: 1.0.1
Summary: simple cli for managing and publishing python packages
Home-page: https://github.com/freeman-lab/pim
Author: freeman-lab
Author-email: the.freeman.lab@gmail.com
License: UNKNOWN
Platform: UNKNOWN
